netxlib/__init__.py
netxlib/crypto.py
netxlib/paramiko.py
netxlib/regex.py
netxlib/rest.py
netxlib/cisco/__init__.py
netxlib/cisco/asa.py
netxlib/cisco/ios.py
netxlib/cisco/iosxr.py
netxlib/cisco/ise.py
netxlib/cisco/nxos.py
netxlib/cisco/ise/__init__.py
netxlib/cisco/ise/create.py
netxlib/cisco/ise/delete.py
netxlib/cisco/ise/read.py
netxlib/cisco/ise/update.py
netxlib/infoblox/__init__.py
netxlib/infoblox/create.py
netxlib/infoblox/delete.py
netxlib/infoblox/read.py
netxlib/infoblox/update.py
netxlib/servicenow/__init__.py
netxlib/servicenow/create.py
netxlib/servicenow/delete.py
netxlib/servicenow/read.py
netxlib/servicenow/update.py
netxlib-0.0.4.dist-info/LICENSE
netxlib-0.0.4.dist-info/METADATA
netxlib-0.0.4.dist-info/WHEEL
netxlib-0.0.4.dist-info/top_level.txt
netxlib-0.0.4.dist-info/RECORD
