Metadata-Version: 2.1
Name: netxlib
Version: 0.0.4
Summary: A collection of network utilities for Python
Home-page: https://github.com/vargyropoulos/netxlib
Author: Vasilis Argyropoulos
Author-email: netxlib@vasilisargyropoulos.com
License: UNKNOWN
Platform: UNKNOWN
Classifier: Development Status :: 1 - Planning
Classifier: Programming Language :: Python :: 3
Classifier: License :: OSI Approved :: MIT License
Classifier: Operating System :: OS Independent
